alu.v
module adder_subtractor (
    input  [7:0] A,
    input  [7:0] B,
    input        ctrl,
    output [7:0] result,
    output       c_out,
    output       V
);
    // Two's complement: invert B and inject carry-in when subtracting
    wire [7:0] B_eff = ctrl ? ~B : B;
    wire       cin = ctrl;

    // Full 8-bit addition, temp[8] is c_out
    wire [8:0] temp = {1'b0, A} + {1'b0, B_eff} + cin;

    // Lower 7 bits only - temp1[7] is C_7 (carry into MSB)
    wire [7:0] temp1 = {1'b0, A[6:0]} + {1'b0, B_eff[6:0]} + cin;

    assign result = temp[7:0];
    assign c_out  = temp[8];
    assign V      = temp[8] ^ temp1[7];

endmodule

module alu (
    input      [7:0] A,
    input      [7:0] B,
    input      [2:0] opcode,
    output reg [7:0] result,
    output reg [3:0] flags
);

    // instantiate the adder-subtractor, OUTSIDE THE PROCEDURAL BLOCK
    wire [7:0] arithmetic_result;
    wire c_out, V;
    adder_subtractor u_add_sub (
            .A     (A),
            .B     (B),
            .ctrl  (opcode[0]),
            .result(arithmetic_result),
            .c_out (c_out),
            .V     (V)
    );

    always @(*) begin

        case (opcode)
            3'b000, 3'b001: result = arithmetic_result;  // same implementation - list with a comma
            3'b010: result = A & B;
            3'b011: result = A | B;
            3'b100: result = A ^ B;
            3'b101: result = ~A;
            3'b110: result = A << 1;
            3'b111: result = A >> 1;
            default: begin
                result = 8'b0;
                flags  = 4'b0;
            end
        endcase

        // flags calculation
        flags[0] = ~|result;  // zero flag, NOR all bits
        flags[1] = ~(opcode[1] | opcode[2]) & c_out;  // c_out flag
        flags[2] = result[7];  // sign flag
        flags[3] = ~(opcode[1] | opcode[2]) & V;
    end

endmodule

alu_tb.v
module alu_tb;

    // Define I/O
    reg [7:0] A, B;  // reg because we set up this value
    reg  [2:0] opcode;
    wire [7:0] result;  // wire because it's driven by the instantiated module
    wire [3:0] flags;

    // instantiate alu
    alu uut (
            .A     (A),
            .B     (B),
            .opcode(opcode),
            .result(result),
            .flags (flags)
    );

    initial begin
        $dumpfile("alu_test.vcd");
        $dumpvars(0, alu_tb);

        $display("Time |   A   |   B   | op | result | flags | expected");
        $display("-----------------------------------------------------");

        // operation tests
        // add
        A      = 8'b00001111;
        B      = 8'b11110000;
        opcode = 3'b000;
        #10;
        $display("%4t | %b | %b | %b | %b | %b | %s", $time, A, B, opcode, result, flags,
                 "result=11111111");

        // sub
        A      = 8'b00001111;
        B      = 8'b11110000;
        opcode = 3'b001;
        #10;
        $display("%4t | %b | %b | %b | %b | %b | %s", $time, A, B, opcode, result, flags,
                 "result=00011111");

        // and
        A      = 8'b10001111;
        B      = 8'b11110000;
        opcode = 3'b010;
        #10;
        $display("%4t | %b | %b | %b | %b | %b | %s", $time, A, B, opcode, result, flags,
                 "result=10000000");

        // or
        A      = 8'b00001111;
        B      = 8'b01110000;
        opcode = 3'b011;
        #10;
        $display("%4t | %b | %b | %b | %b | %b | %s", $time, A, B, opcode, result, flags,
                 "result=01111111");

        // xor
        A      = 8'b01010101;
        B      = 8'b10101011;
        opcode = 3'b100;
        #10;
        $display("%4t | %b | %b | %b | %b | %b | %s", $time, A, B, opcode, result, flags,
                 "result=11111110");

        // not A
        A      = 8'b00000001;
        B      = 8'b00000000;
        opcode = 3'b101;
        #10;
        $display("%4t | %b | %b | %b | %b | %b | %s", $time, A, B, opcode, result, flags,
                 "result=11111110");

        // shift left
        A      = 8'b11111111;
        B      = 8'b00000000;
        opcode = 3'b110;
        #10;
        $display("%4t | %b | %b | %b | %b | %b | %s", $time, A, B, opcode, result, flags,
                 "result=11111110");

        // shift right
        A      = 8'b11111111;
        B      = 8'b00000000;
        opcode = 3'b111;
        #10;
        $display("%4t | %b | %b | %b | %b | %b | %s", $time, A, B, opcode, result, flags,
                 "result=01111111");

        // flag tests
        // zero flag (should be 1)
        A      = 8'b11111111;
        B      = 8'b11111111;
        opcode = 3'b100;
        #10;
        $display("%4t | %b | %b | %b | %b | %b | %s", $time, A, B, opcode, result, flags,
                 "result=00000000, zero=1");

        // carry-out flag (should be 1)
        A      = 8'b11111111;
        B      = 8'b11111111;
        opcode = 3'b000;
        #10;
        $display("%4t | %b | %b | %b | %b | %b | %s", $time, A, B, opcode, result, flags,
                 "result=11111110, carry=1");

        // sign flag (should be 1)
        A      = 8'b00001111;
        B      = 8'b00010000;
        opcode = 3'b001;
        #10;
        $display("%4t | %b | %b | %b | %b | %b | %s", $time, A, B, opcode, result, flags,
                 "result=11111111, sign=1");

        // overflow flag (should be 1)
        A      = 8'b01111111;
        B      = 8'b00000001;
        opcode = 3'b000;
        #10;
        $display("%4t | %b | %b | %b | %b | %b | %s", $time, A, B, opcode, result, flags,
                 "result=10000000, overflow=1");

        $finish;
    end


endmodule

dumps/alu_test.vcd
$date
	Fri May  1 22:16:08 2026
$end
$version
	Icarus Verilog
$end
$timescale
	1s
$end
$scope module alu_tb $end
$var wire 8 ! result [7:0] $end
$var wire 4 " flags [3:0] $end
$var reg 8 # A [7:0] $end
$var reg 8 $ B [7:0] $end
$var reg 3 % opcode [2:0] $end
$scope module uut $end
$var wire 8 & A [7:0] $end
$var wire 8 ' B [7:0] $end
$var wire 3 ( opcode [2:0] $end
$var wire 1 ) c_out $end
$var wire 8 * arithmetic_result [7:0] $end
$var wire 1 + V $end
$var reg 4 , flags [3:0] $end
$var reg 8 - result [7:0] $end
$scope module u_add_sub $end
$var wire 8 . A [7:0] $end
$var wire 8 / B [7:0] $end
$var wire 1 + V $end
$var wire 1 0 cin $end
$var wire 1 1 ctrl $end
$var wire 8 2 temp1 [7:0] $end
$var wire 9 3 temp [8:0] $end
$var wire 8 4 result [7:0] $end
$var wire 1 ) c_out $end
$var wire 8 5 B_eff [7:0] $end
$upscope $end
$upscope $end
$upscope $end
$enddefinitions $end
$comment Show the parameter values. $end
$dumpall
$end
#0
$dumpvars
b11110000 5
b11111111 4
b11111111 3
b1111111 2
01
00
b11110000 /
b1111 .
b11111111 -
b100 ,
0+
b11111111 *
0)
b0 (
b11110000 '
b1111 &
b0 %
b11110000 $
b1111 #
b100 "
b11111111 !
$end
#10
b0 "
b0 ,
b11111 !
b11111 -
0+
b11111 *
b11111 4
b1111 5
b11111 3
b11111 2
10
11
b1 %
b1 (
#20
1+
1)
b11110000 5
b1111111 2
00
01
b1111111 *
b1111111 4
b100 "
b100 ,
b10000000 !
b10000000 -
b10 %
b10 (
b101111111 3
b10001111 #
b10001111 &
b10001111 .
#30
0+
b11111 2
10
11
b10001111 5
b10011111 *
b10011111 4
0)
b0 "
b0 ,
b1111111 !
b1111111 -
b11 %
b11 (
b1110000 $
b1110000 '
b1110000 /
b10011111 3
b1111 #
b1111 &
b1111 .
#40
1)
b10101011 5
00
01
b0 *
b0 4
b10000000 2
b100 "
b100 ,
b11111110 !
b11111110 -
b100 %
b100 (
b10101011 $
b10101011 '
b10101011 /
b100000000 3
b1010101 #
b1010101 &
b1010101 .
#50
10
11
b11111111 5
b1 *
b1 4
1)
b10000001 2
b101 %
b101 (
b0 $
b0 '
b0 /
b100000001 3
b1 #
b1 &
b1 .
#60
0)
b0 5
00
01
b11111111 *
b11111111 4
b1111111 2
b110 %
b110 (
b11111111 3
b11111111 #
b11111111 &
b11111111 .
#70
1)
b11111111 5
b0 "
b0 ,
b1111111 !
b1111111 -
b111111111 3
b11111111 2
10
11
b111 %
b111 (
#80
b11111110 *
b11111110 4
b111111110 3
b11111110 2
00
01
b1 "
b1 ,
b0 !
b0 -
b100 %
b100 (
b11111111 $
b11111111 '
b11111111 /
#90
b110 "
b110 ,
b11111110 !
b11111110 -
b0 %
b0 (
#100
0)
b100 "
b100 ,
b11111111 !
b11111111 -
10
11
b11101111 5
b11111111 *
b11111111 4
b1111111 2
b1 %
b1 (
b10000 $
b10000 '
b10000 /
b11111111 3
b1111 #
b1111 &
b1111 .
#110
1+
b1 5
b1100 "
b1100 ,
b10000000 !
b10000000 -
00
01
b10000000 *
b10000000 4
0)
b10000000 2
b0 %
b0 (
b1 $
b1 '
b1 /
b10000000 3
b1111111 #
b1111111 &
b1111111 .
